README.md
setup.py
renderconftree/DataTable.py
renderconftree/__init__.py
renderconftree/exceptions.py
renderconftree/file_parsers.py
renderconftree/filters.py
renderconftree/read.py
renderconftree/render.py
renderconftree/units.py
renderconftree/utils.py
renderconftree.egg-info/PKG-INFO
renderconftree.egg-info/SOURCES.txt
renderconftree.egg-info/dependency_links.txt
renderconftree.egg-info/entry_points.txt
renderconftree.egg-info/requires.txt
renderconftree.egg-info/top_level.txt
renderconftree/scripts/__init__.py
renderconftree/scripts/render_config_file.py